{
    "loans": [
        {
            "interestRate": 6.3,
            "isProjection": false,
            "currentBalance": 10000,
            "description": "Car",
            "remainingTerm": 120
        },
        {
            "interestRate": 4.5,
            "isProjection": false,
            "currentBalance": 200000,
            "description": "House",
            "remainingTerm": 240
        },
        {
            "interestRate": 7.3,
            "isProjection": true,
            "currentBalance": 5000,
            "description": "Jetski",
            "remainingTerm": 60
        }
    ],
    "statements": []
}